{
  "summary": [
    {
      "category": "Books",
      "region": "Central",
      "total_revenue": 443509.07,
      "total_units": 745,
      "num_transactions": 126,
      "avg_order_value": 3519.91
    },
    {
      "category": "Books",
      "region": "East",
      "total_revenue": 430398.27,
      "total_units": 685,
      "num_transactions": 128,
      "avg_order_value": 3362.49
    },
    {
      "category": "Books",
      "region": "North",
      "total_revenue": 471967.35,
      "total_units": 783,
      "num_transactions": 140,
      "avg_order_value": 3371.2
    },
    {
      "category": "Books",
      "region": "South",
      "total_revenue": 517749.16,
      "total_units": 811,
      "num_transactions": 147,
      "avg_order_value": 3522.1
    },
    {
      "category": "Books",
      "region": "West",
      "total_revenue": 413169.09,
      "total_units": 694,
      "num_transactions": 132,
      "avg_order_value": 3130.07
    },
    {
      "category": "Clothing",
      "region": "Central",
      "total_revenue": 387322.18,
      "total_units": 754,
      "num_transactions": 147,
      "avg_order_value": 2634.84
    },
    {
      "category": "Clothing",
      "region": "East",
      "total_revenue": 346212.18,
      "total_units": 804,
      "num_transactions": 147,
      "avg_order_value": 2355.18
    },
    {
      "category": "Clothing",
      "region": "North",
      "total_revenue": 503321.71,
      "total_units": 969,
      "num_transactions": 170,
      "avg_order_value": 2960.72
    },
    {
      "category": "Clothing",
      "region": "South",
      "total_revenue": 418126.94,
      "total_units": 823,
      "num_transactions": 147,
      "avg_order_value": 2844.4
    },
    {
      "category": "Clothing",
      "region": "West",
      "total_revenue": 397147.63,
      "total_units": 841,
      "num_transactions": 153,
      "avg_order_value": 2595.74
    },
    {
      "category": "Electronics",
      "region": "Central",
      "total_revenue": 366614.45,
      "total_units": 746,
      "num_transactions": 131,
      "avg_order_value": 2798.58
    },
    {
      "category": "Electronics",
      "region": "East",
      "total_revenue": 344253.5,
      "total_units": 702,
      "num_transactions": 130,
      "avg_order_value": 2648.1
    },
    {
      "category": "Electronics",
      "region": "North",
      "total_revenue": 379805.41,
      "total_units": 759,
      "num_transactions": 130,
      "avg_order_value": 2921.58
    },
    {
      "category": "Electronics",
      "region": "South",
      "total_revenue": 420848.39,
      "total_units": 796,
      "num_transactions": 144,
      "avg_order_value": 2922.56
    },
    {
      "category": "Electronics",
      "region": "West",
      "total_revenue": 422596.99,
      "total_units": 824,
      "num_transactions": 142,
      "avg_order_value": 2976.04
    },
    {
      "category": "Food & Beverage",
      "region": "Central",
      "total_revenue": 334555.53,
      "total_units": 768,
      "num_transactions": 138,
      "avg_order_value": 2424.32
    },
    {
      "category": "Food & Beverage",
      "region": "East",
      "total_revenue": 372893.38,
      "total_units": 781,
      "num_transactions": 153,
      "avg_order_value": 2437.21
    },
    {
      "category": "Food & Beverage",
      "region": "North",
      "total_revenue": 396761.16,
      "total_units": 820,
      "num_transactions": 146,
      "avg_order_value": 2717.54
    },
    {
      "category": "Food & Beverage",
      "region": "South",
      "total_revenue": 409999.08,
      "total_units": 884,
      "num_transactions": 155,
      "avg_order_value": 2645.16
    },
    {
      "category": "Food & Beverage",
      "region": "West",
      "total_revenue": 422445.52,
      "total_units": 937,
      "num_transactions": 158,
      "avg_order_value": 2673.71
    },
    {
      "category": "Home & Garden",
      "region": "Central",
      "total_revenue": 309409.07,
      "total_units": 534,
      "num_transactions": 98,
      "avg_order_value": 3157.24
    },
    {
      "category": "Home & Garden",
      "region": "East",
      "total_revenue": 260178.39,
      "total_units": 474,
      "num_transactions": 92,
      "avg_order_value": 2828.03
    },
    {
      "category": "Home & Garden",
      "region": "North",
      "total_revenue": 364810.83,
      "total_units": 620,
      "num_transactions": 114,
      "avg_order_value": 3200.1
    },
    {
      "category": "Home & Garden",
      "region": "South",
      "total_revenue": 366543.72,
      "total_units": 657,
      "num_transactions": 112,
      "avg_order_value": 3272.71
    },
    {
      "category": "Home & Garden",
      "region": "West",
      "total_revenue": 296828.79,
      "total_units": 495,
      "num_transactions": 89,
      "avg_order_value": 3335.15
    },
    {
      "category": "Sports",
      "region": "Central",
      "total_revenue": 454093.61,
      "total_units": 916,
      "num_transactions": 168,
      "avg_order_value": 2702.94
    },
    {
      "category": "Sports",
      "region": "East",
      "total_revenue": 521608.34,
      "total_units": 1054,
      "num_transactions": 180,
      "avg_order_value": 2897.82
    },
    {
      "category": "Sports",
      "region": "North",
      "total_revenue": 508244.12,
      "total_units": 1021,
      "num_transactions": 183,
      "avg_order_value": 2777.29
    },
    {
      "category": "Sports",
      "region": "South",
      "total_revenue": 455860.94,
      "total_units": 914,
      "num_transactions": 163,
      "avg_order_value": 2796.69
    },
    {
      "category": "Sports",
      "region": "West",
      "total_revenue": 532125.02,
      "total_units": 918,
      "num_transactions": 159,
      "avg_order_value": 3346.7
    },
    {
      "category": "Toys",
      "region": "Central",
      "total_revenue": 378273.37,
      "total_units": 758,
      "num_transactions": 130,
      "avg_order_value": 2909.8
    },
    {
      "category": "Toys",
      "region": "East",
      "total_revenue": 462939.37,
      "total_units": 846,
      "num_transactions": 151,
      "avg_order_value": 3065.82
    },
    {
      "category": "Toys",
      "region": "North",
      "total_revenue": 535192.34,
      "total_units": 1024,
      "num_transactions": 184,
      "avg_order_value": 2908.65
    },
    {
      "category": "Toys",
      "region": "South",
      "total_revenue": 476442.57,
      "total_units": 873,
      "num_transactions": 159,
      "avg_order_value": 2996.49
    },
    {
      "category": "Toys",
      "region": "West",
      "total_revenue": 455223.09,
      "total_units": 874,
      "num_transactions": 154,
      "avg_order_value": 2955.99
    }
  ],
  "monthly": [
    {
      "category": "Books",
      "year_month": "2025-01",
      "region": "Central",
      "monthly_revenue": 13146.85
    },
    {
      "category": "Books",
      "year_month": "2025-01",
      "region": "East",
      "monthly_revenue": 39033.93
    },
    {
      "category": "Books",
      "year_month": "2025-01",
      "region": "North",
      "monthly_revenue": 20633.05
    },
    {
      "category": "Books",
      "year_month": "2025-01",
      "region": "South",
      "monthly_revenue": 14571.66
    },
    {
      "category": "Books",
      "year_month": "2025-01",
      "region": "West",
      "monthly_revenue": 18373.52
    },
    {
      "category": "Books",
      "year_month": "2025-02",
      "region": "Central",
      "monthly_revenue": 16565.66
    },
    {
      "category": "Books",
      "year_month": "2025-02",
      "region": "East",
      "monthly_revenue": 32602.46
    },
    {
      "category": "Books",
      "year_month": "2025-02",
      "region": "North",
      "monthly_revenue": 13417.12
    },
    {
      "category": "Books",
      "year_month": "2025-02",
      "region": "South",
      "monthly_revenue": 21621.67
    },
    {
      "category": "Books",
      "year_month": "2025-02",
      "region": "West",
      "monthly_revenue": 20630.97
    },
    {
      "category": "Books",
      "year_month": "2025-03",
      "region": "Central",
      "monthly_revenue": 25413.18
    },
    {
      "category": "Books",
      "year_month": "2025-03",
      "region": "East",
      "monthly_revenue": 20970.84
    },
    {
      "category": "Books",
      "year_month": "2025-03",
      "region": "North",
      "monthly_revenue": 51764.59
    },
    {
      "category": "Books",
      "year_month": "2025-03",
      "region": "South",
      "monthly_revenue": 20475.74
    },
    {
      "category": "Books",
      "year_month": "2025-03",
      "region": "West",
      "monthly_revenue": 19238.02
    },
    {
      "category": "Books",
      "year_month": "2025-04",
      "region": "Central",
      "monthly_revenue": 37972.62
    },
    {
      "category": "Books",
      "year_month": "2025-04",
      "region": "East",
      "monthly_revenue": 15620.34
    },
    {
      "category": "Books",
      "year_month": "2025-04",
      "region": "North",
      "monthly_revenue": 2013.3
    },
    {
      "category": "Books",
      "year_month": "2025-04",
      "region": "South",
      "monthly_revenue": 26250.73
    },
    {
      "category": "Books",
      "year_month": "2025-04",
      "region": "West",
      "monthly_revenue": 13960.12
    },
    {
      "category": "Books",
      "year_month": "2025-05",
      "region": "Central",
      "monthly_revenue": 18245.5
    },
    {
      "category": "Books",
      "year_month": "2025-05",
      "region": "East",
      "monthly_revenue": 18026.77
    },
    {
      "category": "Books",
      "year_month": "2025-05",
      "region": "North",
      "monthly_revenue": 19175.64
    },
    {
      "category": "Books",
      "year_month": "2025-05",
      "region": "South",
      "monthly_revenue": 6974.82
    },
    {
      "category": "Books",
      "year_month": "2025-05",
      "region": "West",
      "monthly_revenue": 17013.4
    },
    {
      "category": "Books",
      "year_month": "2025-06",
      "region": "Central",
      "monthly_revenue": 11952.94
    },
    {
      "category": "Books",
      "year_month": "2025-06",
      "region": "East",
      "monthly_revenue": 20586.59
    },
    {
      "category": "Books",
      "year_month": "2025-06",
      "region": "North",
      "monthly_revenue": 25205.66
    },
    {
      "category": "Books",
      "year_month": "2025-06",
      "region": "South",
      "monthly_revenue": 37472.19
    },
    {
      "category": "Books",
      "year_month": "2025-06",
      "region": "West",
      "monthly_revenue": 25565.7
    },
    {
      "category": "Books",
      "year_month": "2025-07",
      "region": "Central",
      "monthly_revenue": 36934.53
    },
    {
      "category": "Books",
      "year_month": "2025-07",
      "region": "East",
      "monthly_revenue": 8428.03
    },
    {
      "category": "Books",
      "year_month": "2025-07",
      "region": "North",
      "monthly_revenue": 24932.74
    },
    {
      "category": "Books",
      "year_month": "2025-07",
      "region": "South",
      "monthly_revenue": 1923.64
    },
    {
      "category": "Books",
      "year_month": "2025-07",
      "region": "West",
      "monthly_revenue": 36179.11
    },
    {
      "category": "Books",
      "year_month": "2025-08",
      "region": "East",
      "monthly_revenue": 34539.96
    },
    {
      "category": "Books",
      "year_month": "2025-08",
      "region": "North",
      "monthly_revenue": 32498.81
    },
    {
      "category": "Books",
      "year_month": "2025-08",
      "region": "South",
      "monthly_revenue": 19083.76
    },
    {
      "category": "Books",
      "year_month": "2025-08",
      "region": "West",
      "monthly_revenue": 33721.26
    },
    {
      "category": "Books",
      "year_month": "2025-09",
      "region": "Central",
      "monthly_revenue": 16401.42
    },
    {
      "category": "Books",
      "year_month": "2025-09",
      "region": "East",
      "monthly_revenue": 33780.45
    },
    {
      "category": "Books",
      "year_month": "2025-09",
      "region": "North",
      "monthly_revenue": 26733.91
    },
    {
      "category": "Books",
      "year_month": "2025-09",
      "region": "South",
      "monthly_revenue": 23755.09
    },
    {
      "category": "Books",
      "year_month": "2025-09",
      "region": "West",
      "monthly_revenue": 18603.51
    },
    {
      "category": "Books",
      "year_month": "2025-10",
      "region": "Central",
      "monthly_revenue": 42772.9
    },
    {
      "category": "Books",
      "year_month": "2025-10",
      "region": "East",
      "monthly_revenue": 30431.91
    },
    {
      "category": "Books",
      "year_month": "2025-10",
      "region": "North",
      "monthly_revenue": 57481.47
    },
    {
      "category": "Books",
      "year_month": "2025-10",
      "region": "South",
      "monthly_revenue": 46115.94
    },
    {
      "category": "Books",
      "year_month": "2025-10",
      "region": "West",
      "monthly_revenue": 39920.97
    },
    {
      "category": "Books",
      "year_month": "2025-11",
      "region": "Central",
      "monthly_revenue": 88708.49
    },
    {
      "category": "Books",
      "year_month": "2025-11",
      "region": "East",
      "monthly_revenue": 39926.83
    },
    {
      "category": "Books",
      "year_month": "2025-11",
      "region": "North",
      "monthly_revenue": 51762.62
    },
    {
      "category": "Books",
      "year_month": "2025-11",
      "region": "South",
      "monthly_revenue": 86780.27
    },
    {
      "category": "Books",
      "year_month": "2025-11",
      "region": "West",
      "monthly_revenue": 35829.09
    },
    {
      "category": "Books",
      "year_month": "2025-12",
      "region": "Central",
      "monthly_revenue": 60396.42
    },
    {
      "category": "Books",
      "year_month": "2025-12",
      "region": "East",
      "monthly_revenue": 85089.05
    },
    {
      "category": "Books",
      "year_month": "2025-12",
      "region": "North",
      "monthly_revenue": 85797.71
    },
    {
      "category": "Books",
      "year_month": "2025-12",
      "region": "South",
      "monthly_revenue": 99184.88
    },
    {
      "category": "Books",
      "year_month": "2025-12",
      "region": "West",
      "monthly_revenue": 79926.41
    },
    {
      "category": "Books",
      "year_month": "2026-01",
      "region": "Central",
      "monthly_revenue": 24044.09
    },
    {
      "category": "Books",
      "year_month": "2026-01",
      "region": "East",
      "monthly_revenue": 13512.01
    },
    {
      "category": "Books",
      "year_month": "2026-01",
      "region": "North",
      "monthly_revenue": 18970.47
    },
    {
      "category": "Books",
      "year_month": "2026-01",
      "region": "South",
      "monthly_revenue": 55080.59
    },
    {
      "category": "Books",
      "year_month": "2026-01",
      "region": "West",
      "monthly_revenue": 12449.54
    },
    {
      "category": "Books",
      "year_month": "2026-02",
      "region": "Central",
      "monthly_revenue": 38830.59
    },
    {
      "category": "Books",
      "year_month": "2026-02",
      "region": "East",
      "monthly_revenue": 26167.1
    },
    {
      "category": "Books",
      "year_month": "2026-02",
      "region": "North",
      "monthly_revenue": 33539.56
    },
    {
      "category": "Books",
      "year_month": "2026-02",
      "region": "South",
      "monthly_revenue": 33566.82
    },
    {
      "category": "Books",
      "year_month": "2026-02",
      "region": "West",
      "monthly_revenue": 22553.15
    },
    {
      "category": "Books",
      "year_month": "2026-03",
      "region": "Central",
      "monthly_revenue": 12123.88
    },
    {
      "category": "Books",
      "year_month": "2026-03",
      "region": "East",
      "monthly_revenue": 11682.0
    },
    {
      "category": "Books",
      "year_month": "2026-03",
      "region": "North",
      "monthly_revenue": 8040.7
    },
    {
      "category": "Books",
      "year_month": "2026-03",
      "region": "South",
      "monthly_revenue": 24891.36
    },
    {
      "category": "Books",
      "year_month": "2026-03",
      "region": "West",
      "monthly_revenue": 19204.32
    },
    {
      "category": "Clothing",
      "year_month": "2025-01",
      "region": "Central",
      "monthly_revenue": 15186.14
    },
    {
      "category": "Clothing",
      "year_month": "2025-01",
      "region": "East",
      "monthly_revenue": 24260.52
    },
    {
      "category": "Clothing",
      "year_month": "2025-01",
      "region": "North",
      "monthly_revenue": 27242.66
    },
    {
      "category": "Clothing",
      "year_month": "2025-01",
      "region": "South",
      "monthly_revenue": 16591.7
    },
    {
      "category": "Clothing",
      "year_month": "2025-01",
      "region": "West",
      "monthly_revenue": 18990.42
    },
    {
      "category": "Clothing",
      "year_month": "2025-02",
      "region": "Central",
      "monthly_revenue": 14490.24
    },
    {
      "category": "Clothing",
      "year_month": "2025-02",
      "region": "East",
      "monthly_revenue": 30236.31
    },
    {
      "category": "Clothing",
      "year_month": "2025-02",
      "region": "North",
      "monthly_revenue": 30565.09
    },
    {
      "category": "Clothing",
      "year_month": "2025-02",
      "region": "South",
      "monthly_revenue": 21517.65
    },
    {
      "category": "Clothing",
      "year_month": "2025-02",
      "region": "West",
      "monthly_revenue": 14134.52
    },
    {
      "category": "Clothing",
      "year_month": "2025-03",
      "region": "Central",
      "monthly_revenue": 28351.68
    },
    {
      "category": "Clothing",
      "year_month": "2025-03",
      "region": "East",
      "monthly_revenue": 15172.01
    },
    {
      "category": "Clothing",
      "year_month": "2025-03",
      "region": "North",
      "monthly_revenue": 33834.71
    },
    {
      "category": "Clothing",
      "year_month": "2025-03",
      "region": "South",
      "monthly_revenue": 8081.94
    },
    {
      "category": "Clothing",
      "year_month": "2025-03",
      "region": "West",
      "monthly_revenue": 27428.48
    },
    {
      "category": "Clothing",
      "year_month": "2025-04",
      "region": "Central",
      "monthly_revenue": 13507.97
    },
    {
      "category": "Clothing",
      "year_month": "2025-04",
      "region": "East",
      "monthly_revenue": 9886.14
    },
    {
      "category": "Clothing",
      "year_month": "2025-04",
      "region": "North",
      "monthly_revenue": 43141.1
    },
    {
      "category": "Clothing",
      "year_month": "2025-04",
      "region": "South",
      "monthly_revenue": 4059.08
    },
    {
      "category": "Clothing",
      "year_month": "2025-04",
      "region": "West",
      "monthly_revenue": 32275.19
    },
    {
      "category": "Clothing",
      "year_month": "2025-05",
      "region": "Central",
      "monthly_revenue": 24619.97
    },
    {
      "category": "Clothing",
      "year_month": "2025-05",
      "region": "East",
      "monthly_revenue": 24834.7
    },
    {
      "category": "Clothing",
      "year_month": "2025-05",
      "region": "North",
      "monthly_revenue": 46500.23
    },
    {
      "category": "Clothing",
      "year_month": "2025-05",
      "region": "South",
      "monthly_revenue": 4879.54
    },
    {
      "category": "Clothing",
      "year_month": "2025-05",
      "region": "West",
      "monthly_revenue": 16109.55
    },
    {
      "category": "Clothing",
      "year_month": "2025-06",
      "region": "Central",
      "monthly_revenue": 15334.54
    },
    {
      "category": "Clothing",
      "year_month": "2025-06",
      "region": "East",
      "monthly_revenue": 18017.07
    },
    {
      "category": "Clothing",
      "year_month": "2025-06",
      "region": "North",
      "monthly_revenue": 16507.84
    },
    {
      "category": "Clothing",
      "year_month": "2025-06",
      "region": "South",
      "monthly_revenue": 49628.38
    },
    {
      "category": "Clothing",
      "year_month": "2025-06",
      "region": "West",
      "monthly_revenue": 13220.95
    },
    {
      "category": "Clothing",
      "year_month": "2025-07",
      "region": "Central",
      "monthly_revenue": 12586.52
    },
    {
      "category": "Clothing",
      "year_month": "2025-07",
      "region": "East",
      "monthly_revenue": 2121.17
    },
    {
      "category": "Clothing",
      "year_month": "2025-07",
      "region": "North",
      "monthly_revenue": 16796.72
    },
    {
      "category": "Clothing",
      "year_month": "2025-07",
      "region": "South",
      "monthly_revenue": 15433.66
    },
    {
      "category": "Clothing",
      "year_month": "2025-07",
      "region": "West",
      "monthly_revenue": 14174.16
    },
    {
      "category": "Clothing",
      "year_month": "2025-08",
      "region": "Central",
      "monthly_revenue": 50592.69
    },
    {
      "category": "Clothing",
      "year_month": "2025-08",
      "region": "East",
      "monthly_revenue": 14045.69
    },
    {
      "category": "Clothing",
      "year_month": "2025-08",
      "region": "North",
      "monthly_revenue": 16638.32
    },
    {
      "category": "Clothing",
      "year_month": "2025-08",
      "region": "South",
      "monthly_revenue": 8637.45
    },
    {
      "category": "Clothing",
      "year_month": "2025-08",
      "region": "West",
      "monthly_revenue": 18520.14
    },
    {
      "category": "Clothing",
      "year_month": "2025-09",
      "region": "Central",
      "monthly_revenue": 19402.65
    },
    {
      "category": "Clothing",
      "year_month": "2025-09",
      "region": "East",
      "monthly_revenue": 11460.08
    },
    {
      "category": "Clothing",
      "year_month": "2025-09",
      "region": "North",
      "monthly_revenue": 9643.58
    },
    {
      "category": "Clothing",
      "year_month": "2025-09",
      "region": "South",
      "monthly_revenue": 16221.11
    },
    {
      "category": "Clothing",
      "year_month": "2025-09",
      "region": "West",
      "monthly_revenue": 30890.59
    },
    {
      "category": "Clothing",
      "year_month": "2025-10",
      "region": "Central",
      "monthly_revenue": 32503.27
    },
    {
      "category": "Clothing",
      "year_month": "2025-10",
      "region": "East",
      "monthly_revenue": 25743.41
    },
    {
      "category": "Clothing",
      "year_month": "2025-10",
      "region": "North",
      "monthly_revenue": 46694.01
    },
    {
      "category": "Clothing",
      "year_month": "2025-10",
      "region": "South",
      "monthly_revenue": 59153.18
    },
    {
      "category": "Clothing",
      "year_month": "2025-10",
      "region": "West",
      "monthly_revenue": 38965.76
    },
    {
      "category": "Clothing",
      "year_month": "2025-11",
      "region": "Central",
      "monthly_revenue": 35311.56
    },
    {
      "category": "Clothing",
      "year_month": "2025-11",
      "region": "East",
      "monthly_revenue": 58609.64
    },
    {
      "category": "Clothing",
      "year_month": "2025-11",
      "region": "North",
      "monthly_revenue": 64803.72
    },
    {
      "category": "Clothing",
      "year_month": "2025-11",
      "region": "South",
      "monthly_revenue": 49837.96
    },
    {
      "category": "Clothing",
      "year_month": "2025-11",
      "region": "West",
      "monthly_revenue": 54802.57
    },
    {
      "category": "Clothing",
      "year_month": "2025-12",
      "region": "Central",
      "monthly_revenue": 70978.88
    },
    {
      "category": "Clothing",
      "year_month": "2025-12",
      "region": "East",
      "monthly_revenue": 48068.57
    },
    {
      "category": "Clothing",
      "year_month": "2025-12",
      "region": "North",
      "monthly_revenue": 82260.44
    },
    {
      "category": "Clothing",
      "year_month": "2025-12",
      "region": "South",
      "monthly_revenue": 76526.9
    },
    {
      "category": "Clothing",
      "year_month": "2025-12",
      "region": "West",
      "monthly_revenue": 62714.39
    },
    {
      "category": "Clothing",
      "year_month": "2026-01",
      "region": "Central",
      "monthly_revenue": 16379.69
    },
    {
      "category": "Clothing",
      "year_month": "2026-01",
      "region": "East",
      "monthly_revenue": 26120.57
    },
    {
      "category": "Clothing",
      "year_month": "2026-01",
      "region": "North",
      "monthly_revenue": 30269.87
    },
    {
      "category": "Clothing",
      "year_month": "2026-01",
      "region": "South",
      "monthly_revenue": 44998.11
    },
    {
      "category": "Clothing",
      "year_month": "2026-01",
      "region": "West",
      "monthly_revenue": 19531.34
    },
    {
      "category": "Clothing",
      "year_month": "2026-02",
      "region": "Central",
      "monthly_revenue": 20048.4
    },
    {
      "category": "Clothing",
      "year_month": "2026-02",
      "region": "East",
      "monthly_revenue": 27207.74
    },
    {
      "category": "Clothing",
      "year_month": "2026-02",
      "region": "North",
      "monthly_revenue": 25558.92
    },
    {
      "category": "Clothing",
      "year_month": "2026-02",
      "region": "South",
      "monthly_revenue": 25593.49
    },
    {
      "category": "Clothing",
      "year_month": "2026-02",
      "region": "West",
      "monthly_revenue": 35389.57
    },
    {
      "category": "Clothing",
      "year_month": "2026-03",
      "region": "Central",
      "monthly_revenue": 18027.98
    },
    {
      "category": "Clothing",
      "year_month": "2026-03",
      "region": "East",
      "monthly_revenue": 10428.56
    },
    {
      "category": "Clothing",
      "year_month": "2026-03",
      "region": "North",
      "monthly_revenue": 12864.5
    },
    {
      "category": "Clothing",
      "year_month": "2026-03",
      "region": "South",
      "monthly_revenue": 16966.79
    },
    {
      "category": "Electronics",
      "year_month": "2025-01",
      "region": "Central",
      "monthly_revenue": 20855.19
    },
    {
      "category": "Electronics",
      "year_month": "2025-01",
      "region": "East",
      "monthly_revenue": 26828.98
    },
    {
      "category": "Electronics",
      "year_month": "2025-01",
      "region": "North",
      "monthly_revenue": 4857.73
    },
    {
      "category": "Electronics",
      "year_month": "2025-01",
      "region": "South",
      "monthly_revenue": 31621.88
    },
    {
      "category": "Electronics",
      "year_month": "2025-01",
      "region": "West",
      "monthly_revenue": 20966.74
    },
    {
      "category": "Electronics",
      "year_month": "2025-02",
      "region": "Central",
      "monthly_revenue": 28674.29
    },
    {
      "category": "Electronics",
      "year_month": "2025-02",
      "region": "East",
      "monthly_revenue": 24152.88
    },
    {
      "category": "Electronics",
      "year_month": "2025-02",
      "region": "North",
      "monthly_revenue": 2974.18
    },
    {
      "category": "Electronics",
      "year_month": "2025-02",
      "region": "South",
      "monthly_revenue": 14117.81
    },
    {
      "category": "Electronics",
      "year_month": "2025-02",
      "region": "West",
      "monthly_revenue": 11114.87
    },
    {
      "category": "Electronics",
      "year_month": "2025-03",
      "region": "Central",
      "monthly_revenue": 28359.98
    },
    {
      "category": "Electronics",
      "year_month": "2025-03",
      "region": "East",
      "monthly_revenue": 29355.49
    },
    {
      "category": "Electronics",
      "year_month": "2025-03",
      "region": "North",
      "monthly_revenue": 12857.37
    },
    {
      "category": "Electronics",
      "year_month": "2025-03",
      "region": "South",
      "monthly_revenue": 18240.81
    },
    {
      "category": "Electronics",
      "year_month": "2025-03",
      "region": "West",
      "monthly_revenue": 32904.83
    },
    {
      "category": "Electronics",
      "year_month": "2025-04",
      "region": "Central",
      "monthly_revenue": 14563.55
    },
    {
      "category": "Electronics",
      "year_month": "2025-04",
      "region": "East",
      "monthly_revenue": 8383.59
    },
    {
      "category": "Electronics",
      "year_month": "2025-04",
      "region": "North",
      "monthly_revenue": 26663.49
    },
    {
      "category": "Electronics",
      "year_month": "2025-04",
      "region": "South",
      "monthly_revenue": 19504.56
    },
    {
      "category": "Electronics",
      "year_month": "2025-04",
      "region": "West",
      "monthly_revenue": 18209.55
    },
    {
      "category": "Electronics",
      "year_month": "2025-05",
      "region": "Central",
      "monthly_revenue": 34562.42
    },
    {
      "category": "Electronics",
      "year_month": "2025-05",
      "region": "East",
      "monthly_revenue": 3773.83
    },
    {
      "category": "Electronics",
      "year_month": "2025-05",
      "region": "North",
      "monthly_revenue": 3583.83
    },
    {
      "category": "Electronics",
      "year_month": "2025-05",
      "region": "South",
      "monthly_revenue": 34454.13
    },
    {
      "category": "Electronics",
      "year_month": "2025-05",
      "region": "West",
      "monthly_revenue": 30744.68
    },
    {
      "category": "Electronics",
      "year_month": "2025-06",
      "region": "Central",
      "monthly_revenue": 9209.59
    },
    {
      "category": "Electronics",
      "year_month": "2025-06",
      "region": "East",
      "monthly_revenue": 1149.7
    },
    {
      "category": "Electronics",
      "year_month": "2025-06",
      "region": "North",
      "monthly_revenue": 8872.16
    },
    {
      "category": "Electronics",
      "year_month": "2025-06",
      "region": "South",
      "monthly_revenue": 26346.12
    },
    {
      "category": "Electronics",
      "year_month": "2025-06",
      "region": "West",
      "monthly_revenue": 23285.59
    },
    {
      "category": "Electronics",
      "year_month": "2025-07",
      "region": "Central",
      "monthly_revenue": 27583.04
    },
    {
      "category": "Electronics",
      "year_month": "2025-07",
      "region": "East",
      "monthly_revenue": 15837.27
    },
    {
      "category": "Electronics",
      "year_month": "2025-07",
      "region": "North",
      "monthly_revenue": 21458.9
    },
    {
      "category": "Electronics",
      "year_month": "2025-07",
      "region": "South",
      "monthly_revenue": 6748.18
    },
    {
      "category": "Electronics",
      "year_month": "2025-07",
      "region": "West",
      "monthly_revenue": 6973.11
    },
    {
      "category": "Electronics",
      "year_month": "2025-08",
      "region": "Central",
      "monthly_revenue": 7025.38
    },
    {
      "category": "Electronics",
      "year_month": "2025-08",
      "region": "East",
      "monthly_revenue": 10666.06
    },
    {
      "category": "Electronics",
      "year_month": "2025-08",
      "region": "North",
      "monthly_revenue": 19833.24
    },
    {
      "category": "Electronics",
      "year_month": "2025-08",
      "region": "South",
      "monthly_revenue": 15249.58
    },
    {
      "category": "Electronics",
      "year_month": "2025-08",
      "region": "West",
      "monthly_revenue": 38211.23
    },
    {
      "category": "Electronics",
      "year_month": "2025-09",
      "region": "Central",
      "monthly_revenue": 10233.2
    },
    {
      "category": "Electronics",
      "year_month": "2025-09",
      "region": "East",
      "monthly_revenue": 41591.76
    },
    {
      "category": "Electronics",
      "year_month": "2025-09",
      "region": "North",
      "monthly_revenue": 22445.51
    },
    {
      "category": "Electronics",
      "year_month": "2025-09",
      "region": "South",
      "monthly_revenue": 24517.18
    },
    {
      "category": "Electronics",
      "year_month": "2025-09",
      "region": "West",
      "monthly_revenue": 17702.67
    },
    {
      "category": "Electronics",
      "year_month": "2025-10",
      "region": "Central",
      "monthly_revenue": 24778.21
    },
    {
      "category": "Electronics",
      "year_month": "2025-10",
      "region": "East",
      "monthly_revenue": 35791.2
    },
    {
      "category": "Electronics",
      "year_month": "2025-10",
      "region": "North",
      "monthly_revenue": 30764.8
    },
    {
      "category": "Electronics",
      "year_month": "2025-10",
      "region": "South",
      "monthly_revenue": 35540.94
    },
    {
      "category": "Electronics",
      "year_month": "2025-10",
      "region": "West",
      "monthly_revenue": 36184.49
    },
    {
      "category": "Electronics",
      "year_month": "2025-11",
      "region": "Central",
      "monthly_revenue": 60810.76
    },
    {
      "category": "Electronics",
      "year_month": "2025-11",
      "region": "East",
      "monthly_revenue": 30761.06
    },
    {
      "category": "Electronics",
      "year_month": "2025-11",
      "region": "North",
      "monthly_revenue": 78555.5
    },
    {
      "category": "Electronics",
      "year_month": "2025-11",
      "region": "South",
      "monthly_revenue": 63722.69
    },
    {
      "category": "Electronics",
      "year_month": "2025-11",
      "region": "West",
      "monthly_revenue": 68019.04
    },
    {
      "category": "Electronics",
      "year_month": "2025-12",
      "region": "Central",
      "monthly_revenue": 51563.42
    },
    {
      "category": "Electronics",
      "year_month": "2025-12",
      "region": "East",
      "monthly_revenue": 59782.48
    },
    {
      "category": "Electronics",
      "year_month": "2025-12",
      "region": "North",
      "monthly_revenue": 73048.48
    },
    {
      "category": "Electronics",
      "year_month": "2025-12",
      "region": "South",
      "monthly_revenue": 64462.34
    },
    {
      "category": "Electronics",
      "year_month": "2025-12",
      "region": "West",
      "monthly_revenue": 37994.17
    },
    {
      "category": "Electronics",
      "year_month": "2026-01",
      "region": "Central",
      "monthly_revenue": 16398.88
    },
    {
      "category": "Electronics",
      "year_month": "2026-01",
      "region": "East",
      "monthly_revenue": 20648.81
    },
    {
      "category": "Electronics",
      "year_month": "2026-01",
      "region": "North",
      "monthly_revenue": 20851.9
    },
    {
      "category": "Electronics",
      "year_month": "2026-01",
      "region": "South",
      "monthly_revenue": 30887.49
    },
    {
      "category": "Electronics",
      "year_month": "2026-01",
      "region": "West",
      "monthly_revenue": 22489.97
    },
    {
      "category": "Electronics",
      "year_month": "2026-02",
      "region": "Central",
      "monthly_revenue": 20316.08
    },
    {
      "category": "Electronics",
      "year_month": "2026-02",
      "region": "East",
      "monthly_revenue": 31804.79
    },
    {
      "category": "Electronics",
      "year_month": "2026-02",
      "region": "North",
      "monthly_revenue": 23330.23
    },
    {
      "category": "Electronics",
      "year_month": "2026-02",
      "region": "South",
      "monthly_revenue": 14915.29
    },
    {
      "category": "Electronics",
      "year_month": "2026-02",
      "region": "West",
      "monthly_revenue": 21311.79
    },
    {
      "category": "Electronics",
      "year_month": "2026-03",
      "region": "Central",
      "monthly_revenue": 11680.46
    },
    {
      "category": "Electronics",
      "year_month": "2026-03",
      "region": "East",
      "monthly_revenue": 3725.6
    },
    {
      "category": "Electronics",
      "year_month": "2026-03",
      "region": "North",
      "monthly_revenue": 29708.09
    },
    {
      "category": "Electronics",
      "year_month": "2026-03",
      "region": "South",
      "monthly_revenue": 20519.39
    },
    {
      "category": "Electronics",
      "year_month": "2026-03",
      "region": "West",
      "monthly_revenue": 36484.26
    },
    {
      "category": "Food & Beverage",
      "year_month": "2025-01",
      "region": "Central",
      "monthly_revenue": 5375.8
    },
    {
      "category": "Food & Beverage",
      "year_month": "2025-01",
      "region": "East",
      "monthly_revenue": 17966.25
    },
    {
      "category": "Food & Beverage",
      "year_month": "2025-01",
      "region": "North",
      "monthly_revenue": 20584.25
    },
    {
      "category": "Food & Beverage",
      "year_month": "2025-01",
      "region": "South",
      "monthly_revenue": 18448.79
    },
    {
      "category": "Food & Beverage",
      "year_month": "2025-01",
      "region": "West",
      "monthly_revenue": 16288.04
    },
    {
      "category": "Food & Beverage",
      "year_month": "2025-02",
      "region": "Central",
      "monthly_revenue": 13110.27
    },
    {
      "category": "Food & Beverage",
      "year_month": "2025-02",
      "region": "East",
      "monthly_revenue": 15313.23
    },
    {
      "category": "Food & Beverage",
      "year_month": "2025-02",
      "region": "North",
      "monthly_revenue": 23526.19
    },
    {
      "category": "Food & Beverage",
      "year_month": "2025-02",
      "region": "South",
      "monthly_revenue": 33986.67
    },
    {
      "category": "Food & Beverage",
      "year_month": "2025-02",
      "region": "West",
      "monthly_revenue": 13176.6
    },
    {
      "category": "Food & Beverage",
      "year_month": "2025-03",
      "region": "Central",
      "monthly_revenue": 26656.35
    },
    {
      "category": "Food & Beverage",
      "year_month": "2025-03",
      "region": "East",
      "monthly_revenue": 32207.74
    },
    {
      "category": "Food & Beverage",
      "year_month": "2025-03",
      "region": "North",
      "monthly_revenue": 12854.55
    },
    {
      "category": "Food & Beverage",
      "year_month": "2025-03",
      "region": "South",
      "monthly_revenue": 41976.21
    },
    {
      "category": "Food & Beverage",
      "year_month": "2025-03",
      "region": "West",
      "monthly_revenue": 25777.39
    },
    {
      "category": "Food & Beverage",
      "year_month": "2025-04",
      "region": "Central",
      "monthly_revenue": 16346.47
    },
    {
      "category": "Food & Beverage",
      "year_month": "2025-04",
      "region": "East",
      "monthly_revenue": 6774.7
    },
    {
      "category": "Food & Beverage",
      "year_month": "2025-04",
      "region": "North",
      "monthly_revenue": 32075.31
    },
    {
      "category": "Food & Beverage",
      "year_month": "2025-04",
      "region": "South",
      "monthly_revenue": 29523.95
    },
    {
      "category": "Food & Beverage",
      "year_month": "2025-04",
      "region": "West",
      "monthly_revenue": 6058.43
    },
    {
      "category": "Food & Beverage",
      "year_month": "2025-05",
      "region": "Central",
      "monthly_revenue": 8422.29
    },
    {
      "category": "Food & Beverage",
      "year_month": "2025-05",
      "region": "East",
      "monthly_revenue": 14686.48
    },
    {
      "category": "Food & Beverage",
      "year_month": "2025-05",
      "region": "North",
      "monthly_revenue": 6212.18
    },
    {
      "category": "Food & Beverage",
      "year_month": "2025-05",
      "region": "South",
      "monthly_revenue": 16969.88
    },
    {
      "category": "Food & Beverage",
      "year_month": "2025-05",
      "region": "West",
      "monthly_revenue": 16576.64
    },
    {
      "category": "Food & Beverage",
      "year_month": "2025-06",
      "region": "Central",
      "monthly_revenue": 8500.55
    },
    {
      "category": "Food & Beverage",
      "year_month": "2025-06",
      "region": "East",
      "monthly_revenue": 12725.77
    },
    {
      "category": "Food & Beverage",
      "year_month": "2025-06",
      "region": "North",
      "monthly_revenue": 14540.72
    },
    {
      "category": "Food & Beverage",
      "year_month": "2025-06",
      "region": "South",
      "monthly_revenue": 8724.17
    },
    {
      "category": "Food & Beverage",
      "year_month": "2025-06",
      "region": "West",
      "monthly_revenue": 9555.9
    },
    {
      "category": "Food & Beverage",
      "year_month": "2025-07",
      "region": "Central",
      "monthly_revenue": 24726.54
    },
    {
      "category": "Food & Beverage",
      "year_month": "2025-07",
      "region": "East",
      "monthly_revenue": 15436.12
    },
    {
      "category": "Food & Beverage",
      "year_month": "2025-07",
      "region": "North",
      "monthly_revenue": 17475.48
    },
    {
      "category": "Food & Beverage",
      "year_month": "2025-07",
      "region": "South",
      "monthly_revenue": 9490.44
    },
    {
      "category": "Food & Beverage",
      "year_month": "2025-07",
      "region": "West",
      "monthly_revenue": 40054.6
    },
    {
      "category": "Food & Beverage",
      "year_month": "2025-08",
      "region": "Central",
      "monthly_revenue": 20845.78
    },
    {
      "category": "Food & Beverage",
      "year_month": "2025-08",
      "region": "East",
      "monthly_revenue": 12240.7
    },
    {
      "category": "Food & Beverage",
      "year_month": "2025-08",
      "region": "North",
      "monthly_revenue": 12023.66
    },
    {
      "category": "Food & Beverage",
      "year_month": "2025-08",
      "region": "South",
      "monthly_revenue": 27776.02
    },
    {
      "category": "Food & Beverage",
      "year_month": "2025-08",
      "region": "West",
      "monthly_revenue": 21507.84
    },
    {
      "category": "Food & Beverage",
      "year_month": "2025-09",
      "region": "Central",
      "monthly_revenue": 1584.12
    },
    {
      "category": "Food & Beverage",
      "year_month": "2025-09",
      "region": "East",
      "monthly_revenue": 32703.37
    },
    {
      "category": "Food & Beverage",
      "year_month": "2025-09",
      "region": "North",
      "monthly_revenue": 12030.8
    },
    {
      "category": "Food & Beverage",
      "year_month": "2025-09",
      "region": "South",
      "monthly_revenue": 17637.55
    },
    {
      "category": "Food & Beverage",
      "year_month": "2025-09",
      "region": "West",
      "monthly_revenue": 16408.72
    },
    {
      "category": "Food & Beverage",
      "year_month": "2025-10",
      "region": "Central",
      "monthly_revenue": 21304.11
    },
    {
      "category": "Food & Beverage",
      "year_month": "2025-10",
      "region": "East",
      "monthly_revenue": 26518.63
    },
    {
      "category": "Food & Beverage",
      "year_month": "2025-10",
      "region": "North",
      "monthly_revenue": 46738.92
    },
    {
      "category": "Food & Beverage",
      "year_month": "2025-10",
      "region": "South",
      "monthly_revenue": 28779.17
    },
    {
      "category": "Food & Beverage",
      "year_month": "2025-10",
      "region": "West",
      "monthly_revenue": 19958.49
    },
    {
      "category": "Food & Beverage",
      "year_month": "2025-11",
      "region": "Central",
      "monthly_revenue": 47843.0
    },
    {
      "category": "Food & Beverage",
      "year_month": "2025-11",
      "region": "East",
      "monthly_revenue": 55501.32
    },
    {
      "category": "Food & Beverage",
      "year_month": "2025-11",
      "region": "North",
      "monthly_revenue": 79386.13
    },
    {
      "category": "Food & Beverage",
      "year_month": "2025-11",
      "region": "South",
      "monthly_revenue": 54534.03
    },
    {
      "category": "Food & Beverage",
      "year_month": "2025-11",
      "region": "West",
      "monthly_revenue": 77921.28
    },
    {
      "category": "Food & Beverage",
      "year_month": "2025-12",
      "region": "Central",
      "monthly_revenue": 72704.11
    },
    {
      "category": "Food & Beverage",
      "year_month": "2025-12",
      "region": "East",
      "monthly_revenue": 81512.6
    },
    {
      "category": "Food & Beverage",
      "year_month": "2025-12",
      "region": "North",
      "monthly_revenue": 56996.74
    },
    {
      "category": "Food & Beverage",
      "year_month": "2025-12",
      "region": "South",
      "monthly_revenue": 36124.69
    },
    {
      "category": "Food & Beverage",
      "year_month": "2025-12",
      "region": "West",
      "monthly_revenue": 65721.01
    },
    {
      "category": "Food & Beverage",
      "year_month": "2026-01",
      "region": "Central",
      "monthly_revenue": 26120.58
    },
    {
      "category": "Food & Beverage",
      "year_month": "2026-01",
      "region": "East",
      "monthly_revenue": 22094.15
    },
    {
      "category": "Food & Beverage",
      "year_month": "2026-01",
      "region": "North",
      "monthly_revenue": 19293.68
    },
    {
      "category": "Food & Beverage",
      "year_month": "2026-01",
      "region": "South",
      "monthly_revenue": 26711.13
    },
    {
      "category": "Food & Beverage",
      "year_month": "2026-01",
      "region": "West",
      "monthly_revenue": 60329.54
    },
    {
      "category": "Food & Beverage",
      "year_month": "2026-02",
      "region": "Central",
      "monthly_revenue": 33022.94
    },
    {
      "category": "Food & Beverage",
      "year_month": "2026-02",
      "region": "East",
      "monthly_revenue": 23813.82
    },
    {
      "category": "Food & Beverage",
      "year_month": "2026-02",
      "region": "North",
      "monthly_revenue": 30579.91
    },
    {
      "category": "Food & Beverage",
      "year_month": "2026-02",
      "region": "South",
      "monthly_revenue": 38593.78
    },
    {
      "category": "Food & Beverage",
      "year_month": "2026-02",
      "region": "West",
      "monthly_revenue": 24380.14
    },
    {
      "category": "Food & Beverage",
      "year_month": "2026-03",
      "region": "Central",
      "monthly_revenue": 7992.62
    },
    {
      "category": "Food & Beverage",
      "year_month": "2026-03",
      "region": "East",
      "monthly_revenue": 3398.5
    },
    {
      "category": "Food & Beverage",
      "year_month": "2026-03",
      "region": "North",
      "monthly_revenue": 12442.64
    },
    {
      "category": "Food & Beverage",
      "year_month": "2026-03",
      "region": "South",
      "monthly_revenue": 20722.6
    },
    {
      "category": "Food & Beverage",
      "year_month": "2026-03",
      "region": "West",
      "monthly_revenue": 8730.9
    },
    {
      "category": "Home & Garden",
      "year_month": "2025-01",
      "region": "Central",
      "monthly_revenue": 12970.24
    },
    {
      "category": "Home & Garden",
      "year_month": "2025-01",
      "region": "East",
      "monthly_revenue": 9887.73
    },
    {
      "category": "Home & Garden",
      "year_month": "2025-01",
      "region": "North",
      "monthly_revenue": 25471.77
    },
    {
      "category": "Home & Garden",
      "year_month": "2025-01",
      "region": "South",
      "monthly_revenue": 8597.07
    },
    {
      "category": "Home & Garden",
      "year_month": "2025-01",
      "region": "West",
      "monthly_revenue": 12474.18
    },
    {
      "category": "Home & Garden",
      "year_month": "2025-02",
      "region": "Central",
      "monthly_revenue": 4222.91
    },
    {
      "category": "Home & Garden",
      "year_month": "2025-02",
      "region": "East",
      "monthly_revenue": 21756.2
    },
    {
      "category": "Home & Garden",
      "year_month": "2025-02",
      "region": "North",
      "monthly_revenue": 6387.06
    },
    {
      "category": "Home & Garden",
      "year_month": "2025-02",
      "region": "South",
      "monthly_revenue": 4428.22
    },
    {
      "category": "Home & Garden",
      "year_month": "2025-02",
      "region": "West",
      "monthly_revenue": 3282.06
    },
    {
      "category": "Home & Garden",
      "year_month": "2025-03",
      "region": "Central",
      "monthly_revenue": 19342.26
    },
    {
      "category": "Home & Garden",
      "year_month": "2025-03",
      "region": "East",
      "monthly_revenue": 7440.12
    },
    {
      "category": "Home & Garden",
      "year_month": "2025-03",
      "region": "North",
      "monthly_revenue": 21214.48
    },
    {
      "category": "Home & Garden",
      "year_month": "2025-03",
      "region": "South",
      "monthly_revenue": 5718.9
    },
    {
      "category": "Home & Garden",
      "year_month": "2025-03",
      "region": "West",
      "monthly_revenue": 13863.98
    },
    {
      "category": "Home & Garden",
      "year_month": "2025-04",
      "region": "Central",
      "monthly_revenue": 19848.66
    },
    {
      "category": "Home & Garden",
      "year_month": "2025-04",
      "region": "North",
      "monthly_revenue": 13227.88
    },
    {
      "category": "Home & Garden",
      "year_month": "2025-04",
      "region": "South",
      "monthly_revenue": 18245.68
    },
    {
      "category": "Home & Garden",
      "year_month": "2025-04",
      "region": "West",
      "monthly_revenue": 10997.36
    },
    {
      "category": "Home & Garden",
      "year_month": "2025-05",
      "region": "Central",
      "monthly_revenue": 18943.78
    },
    {
      "category": "Home & Garden",
      "year_month": "2025-05",
      "region": "East",
      "monthly_revenue": 1902.62
    },
    {
      "category": "Home & Garden",
      "year_month": "2025-05",
      "region": "North",
      "monthly_revenue": 15142.21
    },
    {
      "category": "Home & Garden",
      "year_month": "2025-05",
      "region": "South",
      "monthly_revenue": 36158.49
    },
    {
      "category": "Home & Garden",
      "year_month": "2025-05",
      "region": "West",
      "monthly_revenue": 4718.65
    },
    {
      "category": "Home & Garden",
      "year_month": "2025-06",
      "region": "Central",
      "monthly_revenue": 9983.13
    },
    {
      "category": "Home & Garden",
      "year_month": "2025-06",
      "region": "East",
      "monthly_revenue": 15798.95
    },
    {
      "category": "Home & Garden",
      "year_month": "2025-06",
      "region": "North",
      "monthly_revenue": 8126.19
    },
    {
      "category": "Home & Garden",
      "year_month": "2025-06",
      "region": "South",
      "monthly_revenue": 17045.27
    },
    {
      "category": "Home & Garden",
      "year_month": "2025-06",
      "region": "West",
      "monthly_revenue": 11540.19
    },
    {
      "category": "Home & Garden",
      "year_month": "2025-07",
      "region": "Central",
      "monthly_revenue": 14640.12
    },
    {
      "category": "Home & Garden",
      "year_month": "2025-07",
      "region": "East",
      "monthly_revenue": 5966.89
    },
    {
      "category": "Home & Garden",
      "year_month": "2025-07",
      "region": "North",
      "monthly_revenue": 17703.3
    },
    {
      "category": "Home & Garden",
      "year_month": "2025-07",
      "region": "South",
      "monthly_revenue": 18472.89
    },
    {
      "category": "Home & Garden",
      "year_month": "2025-07",
      "region": "West",
      "monthly_revenue": 2769.07
    },
    {
      "category": "Home & Garden",
      "year_month": "2025-08",
      "region": "Central",
      "monthly_revenue": 15597.0
    },
    {
      "category": "Home & Garden",
      "year_month": "2025-08",
      "region": "East",
      "monthly_revenue": 12880.76
    },
    {
      "category": "Home & Garden",
      "year_month": "2025-08",
      "region": "North",
      "monthly_revenue": 32846.95
    },
    {
      "category": "Home & Garden",
      "year_month": "2025-08",
      "region": "South",
      "monthly_revenue": 16588.97
    },
    {
      "category": "Home & Garden",
      "year_month": "2025-08",
      "region": "West",
      "monthly_revenue": 24884.32
    },
    {
      "category": "Home & Garden",
      "year_month": "2025-09",
      "region": "Central",
      "monthly_revenue": 5375.56
    },
    {
      "category": "Home & Garden",
      "year_month": "2025-09",
      "region": "East",
      "monthly_revenue": 23501.41
    },
    {
      "category": "Home & Garden",
      "year_month": "2025-09",
      "region": "North",
      "monthly_revenue": 6885.95
    },
    {
      "category": "Home & Garden",
      "year_month": "2025-09",
      "region": "South",
      "monthly_revenue": 45179.93
    },
    {
      "category": "Home & Garden",
      "year_month": "2025-09",
      "region": "West",
      "monthly_revenue": 9765.94
    },
    {
      "category": "Home & Garden",
      "year_month": "2025-10",
      "region": "Central",
      "monthly_revenue": 10799.41
    },
    {
      "category": "Home & Garden",
      "year_month": "2025-10",
      "region": "East",
      "monthly_revenue": 21640.3
    },
    {
      "category": "Home & Garden",
      "year_month": "2025-10",
      "region": "North",
      "monthly_revenue": 43072.55
    },
    {
      "category": "Home & Garden",
      "year_month": "2025-10",
      "region": "South",
      "monthly_revenue": 47529.29
    },
    {
      "category": "Home & Garden",
      "year_month": "2025-10",
      "region": "West",
      "monthly_revenue": 34156.56
    },
    {
      "category": "Home & Garden",
      "year_month": "2025-11",
      "region": "Central",
      "monthly_revenue": 78128.89
    },
    {
      "category": "Home & Garden",
      "year_month": "2025-11",
      "region": "East",
      "monthly_revenue": 56488.86
    },
    {
      "category": "Home & Garden",
      "year_month": "2025-11",
      "region": "North",
      "monthly_revenue": 92534.27
    },
    {
      "category": "Home & Garden",
      "year_month": "2025-11",
      "region": "South",
      "monthly_revenue": 54870.76
    },
    {
      "category": "Home & Garden",
      "year_month": "2025-11",
      "region": "West",
      "monthly_revenue": 63890.05
    },
    {
      "category": "Home & Garden",
      "year_month": "2025-12",
      "region": "Central",
      "monthly_revenue": 58527.54
    },
    {
      "category": "Home & Garden",
      "year_month": "2025-12",
      "region": "East",
      "monthly_revenue": 37137.76
    },
    {
      "category": "Home & Garden",
      "year_month": "2025-12",
      "region": "North",
      "monthly_revenue": 22680.24
    },
    {
      "category": "Home & Garden",
      "year_month": "2025-12",
      "region": "South",
      "monthly_revenue": 23817.46
    },
    {
      "category": "Home & Garden",
      "year_month": "2025-12",
      "region": "West",
      "monthly_revenue": 31197.3
    },
    {
      "category": "Home & Garden",
      "year_month": "2026-01",
      "region": "Central",
      "monthly_revenue": 8043.59
    },
    {
      "category": "Home & Garden",
      "year_month": "2026-01",
      "region": "East",
      "monthly_revenue": 19393.07
    },
    {
      "category": "Home & Garden",
      "year_month": "2026-01",
      "region": "North",
      "monthly_revenue": 40764.56
    },
    {
      "category": "Home & Garden",
      "year_month": "2026-01",
      "region": "South",
      "monthly_revenue": 32040.9
    },
    {
      "category": "Home & Garden",
      "year_month": "2026-01",
      "region": "West",
      "monthly_revenue": 18544.53
    },
    {
      "category": "Home & Garden",
      "year_month": "2026-02",
      "region": "Central",
      "monthly_revenue": 28690.71
    },
    {
      "category": "Home & Garden",
      "year_month": "2026-02",
      "region": "East",
      "monthly_revenue": 26383.72
    },
    {
      "category": "Home & Garden",
      "year_month": "2026-02",
      "region": "North",
      "monthly_revenue": 16098.12
    },
    {
      "category": "Home & Garden",
      "year_month": "2026-02",
      "region": "South",
      "monthly_revenue": 25326.08
    },
    {
      "category": "Home & Garden",
      "year_month": "2026-02",
      "region": "West",
      "monthly_revenue": 31893.16
    },
    {
      "category": "Home & Garden",
      "year_month": "2026-03",
      "region": "Central",
      "monthly_revenue": 4295.27
    },
    {
      "category": "Home & Garden",
      "year_month": "2026-03",
      "region": "North",
      "monthly_revenue": 2655.3
    },
    {
      "category": "Home & Garden",
      "year_month": "2026-03",
      "region": "South",
      "monthly_revenue": 12523.81
    },
    {
      "category": "Home & Garden",
      "year_month": "2026-03",
      "region": "West",
      "monthly_revenue": 22851.44
    },
    {
      "category": "Sports",
      "year_month": "2025-01",
      "region": "Central",
      "monthly_revenue": 23491.82
    },
    {
      "category": "Sports",
      "year_month": "2025-01",
      "region": "East",
      "monthly_revenue": 34538.84
    },
    {
      "category": "Sports",
      "year_month": "2025-01",
      "region": "North",
      "monthly_revenue": 41374.57
    },
    {
      "category": "Sports",
      "year_month": "2025-01",
      "region": "South",
      "monthly_revenue": 25377.8
    },
    {
      "category": "Sports",
      "year_month": "2025-01",
      "region": "West",
      "monthly_revenue": 23507.76
    },
    {
      "category": "Sports",
      "year_month": "2025-02",
      "region": "Central",
      "monthly_revenue": 28888.45
    },
    {
      "category": "Sports",
      "year_month": "2025-02",
      "region": "East",
      "monthly_revenue": 31026.48
    },
    {
      "category": "Sports",
      "year_month": "2025-02",
      "region": "North",
      "monthly_revenue": 25830.9
    },
    {
      "category": "Sports",
      "year_month": "2025-02",
      "region": "South",
      "monthly_revenue": 12992.21
    },
    {
      "category": "Sports",
      "year_month": "2025-02",
      "region": "West",
      "monthly_revenue": 45525.67
    },
    {
      "category": "Sports",
      "year_month": "2025-03",
      "region": "Central",
      "monthly_revenue": 12775.93
    },
    {
      "category": "Sports",
      "year_month": "2025-03",
      "region": "East",
      "monthly_revenue": 42073.81
    },
    {
      "category": "Sports",
      "year_month": "2025-03",
      "region": "North",
      "monthly_revenue": 24185.78
    },
    {
      "category": "Sports",
      "year_month": "2025-03",
      "region": "South",
      "monthly_revenue": 22313.14
    },
    {
      "category": "Sports",
      "year_month": "2025-03",
      "region": "West",
      "monthly_revenue": 23934.05
    },
    {
      "category": "Sports",
      "year_month": "2025-04",
      "region": "Central",
      "monthly_revenue": 11417.27
    },
    {
      "category": "Sports",
      "year_month": "2025-04",
      "region": "East",
      "monthly_revenue": 38450.17
    },
    {
      "category": "Sports",
      "year_month": "2025-04",
      "region": "North",
      "monthly_revenue": 32984.88
    },
    {
      "category": "Sports",
      "year_month": "2025-04",
      "region": "South",
      "monthly_revenue": 10304.51
    },
    {
      "category": "Sports",
      "year_month": "2025-04",
      "region": "West",
      "monthly_revenue": 19679.0
    },
    {
      "category": "Sports",
      "year_month": "2025-05",
      "region": "Central",
      "monthly_revenue": 32065.56
    },
    {
      "category": "Sports",
      "year_month": "2025-05",
      "region": "East",
      "monthly_revenue": 23524.75
    },
    {
      "category": "Sports",
      "year_month": "2025-05",
      "region": "North",
      "monthly_revenue": 20426.4
    },
    {
      "category": "Sports",
      "year_month": "2025-05",
      "region": "South",
      "monthly_revenue": 15269.14
    },
    {
      "category": "Sports",
      "year_month": "2025-05",
      "region": "West",
      "monthly_revenue": 15439.76
    },
    {
      "category": "Sports",
      "year_month": "2025-06",
      "region": "Central",
      "monthly_revenue": 19154.89
    },
    {
      "category": "Sports",
      "year_month": "2025-06",
      "region": "East",
      "monthly_revenue": 27813.36
    },
    {
      "category": "Sports",
      "year_month": "2025-06",
      "region": "North",
      "monthly_revenue": 22571.54
    },
    {
      "category": "Sports",
      "year_month": "2025-06",
      "region": "South",
      "monthly_revenue": 37250.28
    },
    {
      "category": "Sports",
      "year_month": "2025-06",
      "region": "West",
      "monthly_revenue": 39739.1
    },
    {
      "category": "Sports",
      "year_month": "2025-07",
      "region": "Central",
      "monthly_revenue": 23791.51
    },
    {
      "category": "Sports",
      "year_month": "2025-07",
      "region": "East",
      "monthly_revenue": 20503.0
    },
    {
      "category": "Sports",
      "year_month": "2025-07",
      "region": "North",
      "monthly_revenue": 21690.5
    },
    {
      "category": "Sports",
      "year_month": "2025-07",
      "region": "South",
      "monthly_revenue": 14445.14
    },
    {
      "category": "Sports",
      "year_month": "2025-07",
      "region": "West",
      "monthly_revenue": 18581.19
    },
    {
      "category": "Sports",
      "year_month": "2025-08",
      "region": "Central",
      "monthly_revenue": 18931.44
    },
    {
      "category": "Sports",
      "year_month": "2025-08",
      "region": "East",
      "monthly_revenue": 14603.44
    },
    {
      "category": "Sports",
      "year_month": "2025-08",
      "region": "North",
      "monthly_revenue": 31700.05
    },
    {
      "category": "Sports",
      "year_month": "2025-08",
      "region": "South",
      "monthly_revenue": 32529.96
    },
    {
      "category": "Sports",
      "year_month": "2025-08",
      "region": "West",
      "monthly_revenue": 10902.03
    },
    {
      "category": "Sports",
      "year_month": "2025-09",
      "region": "Central",
      "monthly_revenue": 20597.04
    },
    {
      "category": "Sports",
      "year_month": "2025-09",
      "region": "East",
      "monthly_revenue": 24174.33
    },
    {
      "category": "Sports",
      "year_month": "2025-09",
      "region": "North",
      "monthly_revenue": 42599.12
    },
    {
      "category": "Sports",
      "year_month": "2025-09",
      "region": "South",
      "monthly_revenue": 34047.35
    },
    {
      "category": "Sports",
      "year_month": "2025-09",
      "region": "West",
      "monthly_revenue": 22266.25
    },
    {
      "category": "Sports",
      "year_month": "2025-10",
      "region": "Central",
      "monthly_revenue": 56361.61
    },
    {
      "category": "Sports",
      "year_month": "2025-10",
      "region": "East",
      "monthly_revenue": 34710.92
    },
    {
      "category": "Sports",
      "year_month": "2025-10",
      "region": "North",
      "monthly_revenue": 55563.63
    },
    {
      "category": "Sports",
      "year_month": "2025-10",
      "region": "South",
      "monthly_revenue": 34966.78
    },
    {
      "category": "Sports",
      "year_month": "2025-10",
      "region": "West",
      "monthly_revenue": 53359.58
    },
    {
      "category": "Sports",
      "year_month": "2025-11",
      "region": "Central",
      "monthly_revenue": 73235.3
    },
    {
      "category": "Sports",
      "year_month": "2025-11",
      "region": "East",
      "monthly_revenue": 59779.01
    },
    {
      "category": "Sports",
      "year_month": "2025-11",
      "region": "North",
      "monthly_revenue": 60411.32
    },
    {
      "category": "Sports",
      "year_month": "2025-11",
      "region": "South",
      "monthly_revenue": 53868.21
    },
    {
      "category": "Sports",
      "year_month": "2025-11",
      "region": "West",
      "monthly_revenue": 61641.5
    },
    {
      "category": "Sports",
      "year_month": "2025-12",
      "region": "Central",
      "monthly_revenue": 77386.46
    },
    {
      "category": "Sports",
      "year_month": "2025-12",
      "region": "East",
      "monthly_revenue": 68459.25
    },
    {
      "category": "Sports",
      "year_month": "2025-12",
      "region": "North",
      "monthly_revenue": 53243.88
    },
    {
      "category": "Sports",
      "year_month": "2025-12",
      "region": "South",
      "monthly_revenue": 55163.02
    },
    {
      "category": "Sports",
      "year_month": "2025-12",
      "region": "West",
      "monthly_revenue": 89454.08
    },
    {
      "category": "Sports",
      "year_month": "2026-01",
      "region": "Central",
      "monthly_revenue": 20157.27
    },
    {
      "category": "Sports",
      "year_month": "2026-01",
      "region": "East",
      "monthly_revenue": 39035.91
    },
    {
      "category": "Sports",
      "year_month": "2026-01",
      "region": "North",
      "monthly_revenue": 27723.48
    },
    {
      "category": "Sports",
      "year_month": "2026-01",
      "region": "South",
      "monthly_revenue": 57706.84
    },
    {
      "category": "Sports",
      "year_month": "2026-01",
      "region": "West",
      "monthly_revenue": 38772.78
    },
    {
      "category": "Sports",
      "year_month": "2026-02",
      "region": "Central",
      "monthly_revenue": 26222.81
    },
    {
      "category": "Sports",
      "year_month": "2026-02",
      "region": "East",
      "monthly_revenue": 35590.22
    },
    {
      "category": "Sports",
      "year_month": "2026-02",
      "region": "North",
      "monthly_revenue": 22618.33
    },
    {
      "category": "Sports",
      "year_month": "2026-02",
      "region": "South",
      "monthly_revenue": 35825.27
    },
    {
      "category": "Sports",
      "year_month": "2026-02",
      "region": "West",
      "monthly_revenue": 16875.25
    },
    {
      "category": "Sports",
      "year_month": "2026-03",
      "region": "Central",
      "monthly_revenue": 9616.25
    },
    {
      "category": "Sports",
      "year_month": "2026-03",
      "region": "East",
      "monthly_revenue": 27324.85
    },
    {
      "category": "Sports",
      "year_month": "2026-03",
      "region": "North",
      "monthly_revenue": 25319.74
    },
    {
      "category": "Sports",
      "year_month": "2026-03",
      "region": "South",
      "monthly_revenue": 13801.29
    },
    {
      "category": "Sports",
      "year_month": "2026-03",
      "region": "West",
      "monthly_revenue": 52447.02
    },
    {
      "category": "Toys",
      "year_month": "2025-01",
      "region": "Central",
      "monthly_revenue": 31937.3
    },
    {
      "category": "Toys",
      "year_month": "2025-01",
      "region": "East",
      "monthly_revenue": 13812.22
    },
    {
      "category": "Toys",
      "year_month": "2025-01",
      "region": "North",
      "monthly_revenue": 29276.01
    },
    {
      "category": "Toys",
      "year_month": "2025-01",
      "region": "South",
      "monthly_revenue": 39940.09
    },
    {
      "category": "Toys",
      "year_month": "2025-01",
      "region": "West",
      "monthly_revenue": 17398.85
    },
    {
      "category": "Toys",
      "year_month": "2025-02",
      "region": "Central",
      "monthly_revenue": 11683.87
    },
    {
      "category": "Toys",
      "year_month": "2025-02",
      "region": "East",
      "monthly_revenue": 35470.55
    },
    {
      "category": "Toys",
      "year_month": "2025-02",
      "region": "North",
      "monthly_revenue": 21506.43
    },
    {
      "category": "Toys",
      "year_month": "2025-02",
      "region": "South",
      "monthly_revenue": 16896.74
    },
    {
      "category": "Toys",
      "year_month": "2025-02",
      "region": "West",
      "monthly_revenue": 28603.81
    },
    {
      "category": "Toys",
      "year_month": "2025-03",
      "region": "Central",
      "monthly_revenue": 22540.71
    },
    {
      "category": "Toys",
      "year_month": "2025-03",
      "region": "East",
      "monthly_revenue": 13882.52
    },
    {
      "category": "Toys",
      "year_month": "2025-03",
      "region": "North",
      "monthly_revenue": 35707.62
    },
    {
      "category": "Toys",
      "year_month": "2025-03",
      "region": "South",
      "monthly_revenue": 2124.63
    },
    {
      "category": "Toys",
      "year_month": "2025-03",
      "region": "West",
      "monthly_revenue": 33425.15
    },
    {
      "category": "Toys",
      "year_month": "2025-04",
      "region": "Central",
      "monthly_revenue": 10323.04
    },
    {
      "category": "Toys",
      "year_month": "2025-04",
      "region": "East",
      "monthly_revenue": 54236.24
    },
    {
      "category": "Toys",
      "year_month": "2025-04",
      "region": "North",
      "monthly_revenue": 24125.7
    },
    {
      "category": "Toys",
      "year_month": "2025-04",
      "region": "South",
      "monthly_revenue": 33663.77
    },
    {
      "category": "Toys",
      "year_month": "2025-04",
      "region": "West",
      "monthly_revenue": 34393.26
    },
    {
      "category": "Toys",
      "year_month": "2025-05",
      "region": "Central",
      "monthly_revenue": 7093.54
    },
    {
      "category": "Toys",
      "year_month": "2025-05",
      "region": "East",
      "monthly_revenue": 27570.05
    },
    {
      "category": "Toys",
      "year_month": "2025-05",
      "region": "North",
      "monthly_revenue": 28428.51
    },
    {
      "category": "Toys",
      "year_month": "2025-05",
      "region": "South",
      "monthly_revenue": 14639.84
    },
    {
      "category": "Toys",
      "year_month": "2025-05",
      "region": "West",
      "monthly_revenue": 15638.76
    },
    {
      "category": "Toys",
      "year_month": "2025-06",
      "region": "Central",
      "monthly_revenue": 12392.74
    },
    {
      "category": "Toys",
      "year_month": "2025-06",
      "region": "East",
      "monthly_revenue": 20328.25
    },
    {
      "category": "Toys",
      "year_month": "2025-06",
      "region": "North",
      "monthly_revenue": 24999.43
    },
    {
      "category": "Toys",
      "year_month": "2025-06",
      "region": "South",
      "monthly_revenue": 13698.41
    },
    {
      "category": "Toys",
      "year_month": "2025-06",
      "region": "West",
      "monthly_revenue": 26700.59
    },
    {
      "category": "Toys",
      "year_month": "2025-07",
      "region": "Central",
      "monthly_revenue": 17177.44
    },
    {
      "category": "Toys",
      "year_month": "2025-07",
      "region": "East",
      "monthly_revenue": 26572.01
    },
    {
      "category": "Toys",
      "year_month": "2025-07",
      "region": "North",
      "monthly_revenue": 9967.94
    },
    {
      "category": "Toys",
      "year_month": "2025-07",
      "region": "South",
      "monthly_revenue": 23347.55
    },
    {
      "category": "Toys",
      "year_month": "2025-07",
      "region": "West",
      "monthly_revenue": 40046.29
    },
    {
      "category": "Toys",
      "year_month": "2025-08",
      "region": "Central",
      "monthly_revenue": 19658.12
    },
    {
      "category": "Toys",
      "year_month": "2025-08",
      "region": "East",
      "monthly_revenue": 14484.12
    },
    {
      "category": "Toys",
      "year_month": "2025-08",
      "region": "North",
      "monthly_revenue": 52097.25
    },
    {
      "category": "Toys",
      "year_month": "2025-08",
      "region": "South",
      "monthly_revenue": 40442.35
    },
    {
      "category": "Toys",
      "year_month": "2025-08",
      "region": "West",
      "monthly_revenue": 20017.1
    },
    {
      "category": "Toys",
      "year_month": "2025-09",
      "region": "Central",
      "monthly_revenue": 14931.54
    },
    {
      "category": "Toys",
      "year_month": "2025-09",
      "region": "East",
      "monthly_revenue": 14890.07
    },
    {
      "category": "Toys",
      "year_month": "2025-09",
      "region": "North",
      "monthly_revenue": 58113.9
    },
    {
      "category": "Toys",
      "year_month": "2025-09",
      "region": "South",
      "monthly_revenue": 21778.24
    },
    {
      "category": "Toys",
      "year_month": "2025-09",
      "region": "West",
      "monthly_revenue": 37068.54
    },
    {
      "category": "Toys",
      "year_month": "2025-10",
      "region": "Central",
      "monthly_revenue": 38347.65
    },
    {
      "category": "Toys",
      "year_month": "2025-10",
      "region": "East",
      "monthly_revenue": 35279.61
    },
    {
      "category": "Toys",
      "year_month": "2025-10",
      "region": "North",
      "monthly_revenue": 60918.8
    },
    {
      "category": "Toys",
      "year_month": "2025-10",
      "region": "South",
      "monthly_revenue": 45980.02
    },
    {
      "category": "Toys",
      "year_month": "2025-10",
      "region": "West",
      "monthly_revenue": 23915.92
    },
    {
      "category": "Toys",
      "year_month": "2025-11",
      "region": "Central",
      "monthly_revenue": 60358.45
    },
    {
      "category": "Toys",
      "year_month": "2025-11",
      "region": "East",
      "monthly_revenue": 53341.95
    },
    {
      "category": "Toys",
      "year_month": "2025-11",
      "region": "North",
      "monthly_revenue": 60191.24
    },
    {
      "category": "Toys",
      "year_month": "2025-11",
      "region": "South",
      "monthly_revenue": 42837.34
    },
    {
      "category": "Toys",
      "year_month": "2025-11",
      "region": "West",
      "monthly_revenue": 60767.35
    },
    {
      "category": "Toys",
      "year_month": "2025-12",
      "region": "Central",
      "monthly_revenue": 75295.15
    },
    {
      "category": "Toys",
      "year_month": "2025-12",
      "region": "East",
      "monthly_revenue": 49601.93
    },
    {
      "category": "Toys",
      "year_month": "2025-12",
      "region": "North",
      "monthly_revenue": 68330.16
    },
    {
      "category": "Toys",
      "year_month": "2025-12",
      "region": "South",
      "monthly_revenue": 89941.63
    },
    {
      "category": "Toys",
      "year_month": "2025-12",
      "region": "West",
      "monthly_revenue": 36079.9
    },
    {
      "category": "Toys",
      "year_month": "2026-01",
      "region": "Central",
      "monthly_revenue": 28064.08
    },
    {
      "category": "Toys",
      "year_month": "2026-01",
      "region": "East",
      "monthly_revenue": 55909.99
    },
    {
      "category": "Toys",
      "year_month": "2026-01",
      "region": "North",
      "monthly_revenue": 16041.88
    },
    {
      "category": "Toys",
      "year_month": "2026-01",
      "region": "South",
      "monthly_revenue": 41869.28
    },
    {
      "category": "Toys",
      "year_month": "2026-01",
      "region": "West",
      "monthly_revenue": 36875.39
    },
    {
      "category": "Toys",
      "year_month": "2026-02",
      "region": "Central",
      "monthly_revenue": 22615.75
    },
    {
      "category": "Toys",
      "year_month": "2026-02",
      "region": "East",
      "monthly_revenue": 20352.91
    },
    {
      "category": "Toys",
      "year_month": "2026-02",
      "region": "North",
      "monthly_revenue": 33816.9
    },
    {
      "category": "Toys",
      "year_month": "2026-02",
      "region": "South",
      "monthly_revenue": 21189.02
    },
    {
      "category": "Toys",
      "year_month": "2026-02",
      "region": "West",
      "monthly_revenue": 24871.97
    },
    {
      "category": "Toys",
      "year_month": "2026-03",
      "region": "Central",
      "monthly_revenue": 5853.99
    },
    {
      "category": "Toys",
      "year_month": "2026-03",
      "region": "East",
      "monthly_revenue": 27206.95
    },
    {
      "category": "Toys",
      "year_month": "2026-03",
      "region": "North",
      "monthly_revenue": 11670.57
    },
    {
      "category": "Toys",
      "year_month": "2026-03",
      "region": "South",
      "monthly_revenue": 28093.66
    },
    {
      "category": "Toys",
      "year_month": "2026-03",
      "region": "West",
      "monthly_revenue": 19420.21
    }
  ]
}